snap_html/__init__.py
snap_html/__main__.py
snap_html/py.typed
snap_html-0.6.0.dist-info/METADATA
snap_html-0.6.0.dist-info/WHEEL
snap_html-0.6.0.dist-info/entry_points.txt
snap_html-0.6.0.dist-info/licenses/LICENSE
snap_html-0.6.0.dist-info/RECORD
