Metadata-Version: 2.4
Name: snap-html
Version: 0.6.0
Summary: a robust, modern and high performance Python library for generating image from a html string/html file/url build on top of `playwright`
Project-URL: Homepage, https://github.com/codustry/snap-html
Project-URL: Repository, https://github.com/codustry/snap-html
Author-email: codustry <hello@codustry.com>
License-Expression: MIT
License-File: LICENSE
Classifier: Development Status :: 3 - Alpha
Classifier: Intended Audience :: Developers
Classifier: Operating System :: OS Independent
Classifier: Topic :: Software Development :: Libraries :: Python Modules
Requires-Python: ~=3.8
Requires-Dist: furl>=2.1.0
Requires-Dist: pint>=0.21.1
Requires-Dist: playwright
Requires-Dist: pydantic>=2.10.6
Requires-Dist: pytest>=6.2.5
Requires-Dist: rich>=9.8.2
Requires-Dist: typer[all]>=0.3.2
